renx/__init__.py
renx/__main__.py
renx/findskel.py
renx/main.py
renx/walkdir.py
renx-0.0.7.dist-info/licenses/LICENSE
renx-0.0.7.dist-info/METADATA
renx-0.0.7.dist-info/WHEEL
renx-0.0.7.dist-info/entry_points.txt
renx-0.0.7.dist-info/top_level.txt
renx-0.0.7.dist-info/RECORD
