Metadata-Version: 2.4
Name: renx
Version: 0.0.7
Summary: Advanced file renaming tool with regex and case transformation support
Author: Jet-Logic
License:                     GNU GENERAL PUBLIC LICENSE
Project-URL: Homepage, https://github.com/jet-logic/renx
Project-URL: Documentation, https://github.com/jet-logic/renx#readme
Project-URL: BugTracker, https://github.com/jet-logic/renx/issues
Project-URL: Changelog, https://github.com/jet-logic/renx/releases
Keywords: rename,files,regex,cli,batch
Classifier: Development Status :: 4 - Beta
Classifier: Intended Audience :: Developers
Classifier: Intended Audience :: System Administrators
Classifier: Programming Language :: Python :: 3
Classifier: Operating System :: OS Independent
Classifier: Environment :: Console
Classifier: Topic :: Utilities
Requires-Python: >=3.8
License-File: LICENSE
Provides-Extra: test
Requires-Dist: pytest>=6.0; extra == "test"
Requires-Dist: pytest-cov>=2.0; extra == "test"
Requires-Dist: pytest-mock>=3.0; extra == "test"
Provides-Extra: dev
Requires-Dist: black>=22.0; extra == "dev"
Requires-Dist: flake8>=4.0; extra == "dev"
Requires-Dist: mypy>=0.900; extra == "dev"
Requires-Dist: isort>=5.0; extra == "dev"
Dynamic: license-file
